{
  "$schema": "https://ui.shadcn.com/schema/registry-item.json",
  "name": "animate-fade-out-up-big",
  "cssVars": {
    "theme": {
      "--animate-fade-out-up-big": "fadeOutUpBig 1s"
    }
  },
  "css": {
    "@layer utilities": {
      "@keyframes fadeOutUpBig": {
        "0%": {
          "opacity": "1"
        },
        "100%": {
          "opacity": "0",
          "transform": "translate3d(0, -2000px, 0)"
        }
      }
    }
  },
  "meta": {
    "category": "animations",
    "version": "1.0.0"
  },
  "type": "registry:style"
}